enigma/__init__.py
enigma/cryptodom.py
enigma/keys.py
enigma/prime_euclid.py
enigma/pynacl.py
enigma/rsacipher.py
enigma/vs.py
PyEnigmatic-0.0.3.dist-info/License.txt
PyEnigmatic-0.0.3.dist-info/METADATA
PyEnigmatic-0.0.3.dist-info/WHEEL
PyEnigmatic-0.0.3.dist-info/top_level.txt
PyEnigmatic-0.0.3.dist-info/RECORD
