Metadata-Version: 2.1
Name: PyEnigmatic
Version: 0.0.3
Summary: An enigmatic cryptographic library
Home-page: https://github.com/hamza-yusuff
Author: Hamza Bin Yusuff
Author-email: hbyusuff@uwaterloo.ca
License: MIT LICENSE
Keywords: python,enigma,cryptography,aes,rsa,caesar,vigenere,symmetric,assymetric,key,prime
Platform: UNKNOWN
Requires-Dist: cryptography
Requires-Dist: pynacl
Requires-Dist: pycryptodome
